Quelert/__init__.py
Quelert/pyquelert.py
PyQuelert-1.0.0.dist-info/METADATA
PyQuelert-1.0.0.dist-info/WHEEL
PyQuelert-1.0.0.dist-info/top_level.txt
PyQuelert-1.0.0.dist-info/RECORD
