Metadata-Version: 2.1
Name: PyQuelert
Version: 1.0.0
Summary: Format for files
Author: Georgy2008
Author-email: zadvornow2908@gmail.com
Classifier: Programming Language :: Python :: 3
Classifier: License :: OSI Approved :: MIT License
Classifier: Operating System :: OS Independent
Requires-Python: >=3.6
